<map>
<dec_stones3 x='545' y='278' />
<dec_stones2 x='450' y='289' />
<dec_stones2 x='527' y='336' />
<dec_stones1 x='399' y='284' />
<dec_plant2 x='404' y='280' />
<dec_wood1 x='486' y='275' rotation='22' scaleX='1.41' scaleY='1.36' />
<dec_plant2 x='424' y='290' />
<dec_plant2 x='404' y='290' />
<dec_plant2 x='575' y='280' flipX='YES' />
<dec_plant2 x='555' y='290' flipX='YES' />
<dec_plant2 x='575' y='290' flipX='YES' />
<dec_plant7 x='101' y='513' rotation='15' />
<dec_plant7 x='41' y='483' flipX='YES' />
<dec_plant7 x='80' y='482' rotation='15' scaleX='0.578' scaleY='0.649' alpha='0.6' />
<dec_plant7 x='66' y='513' rotation='-15' scaleX='0.578' scaleY='0.649' alpha='0.6' />
<dec_plant7 x='9' y='493' scaleX='0.884' scaleY='0.756' />
<dec_plant7 x='135' y='561' rotation='45' />
<dec_plant7 x='122' y='542' scaleX='0.884' scaleY='0.756' />
<dec_plant5 x='718' y='71' rotation='-35' alpha='0.6' />
<dec_plant5 x='746' y='60' rotation='-5' scaleX='0.641' scaleY='0.692' alpha='0.6' />
<dec_plant7 x='778' y='58' rotation='10' />
<dec_plant5 x='726' y='55' rotation='-20' scaleX='1.29' scaleY='1.33' alpha='0.6' />
<dec_plant5 x='710' y='82' rotation='-50' scaleX='0.641' scaleY='0.692' alpha='0.6' />
<dec_plant5 x='778' y='58' rotation='-20' />
<dec_plant5 x='810' y='68' rotation='10' scaleX='0.641' scaleY='0.692' />
<dec_plant5 x='688' y='62' rotation='-5' scaleX='1.15' scaleY='1.71' />
<dec_plant5 x='824' y='67' rotation='10' scaleX='0.641' scaleY='0.692' />
<dec_mask x='766' y='100' />
<redCell1 x='142' y='629' />
<redCell2 x='677' y='369' />
<ExitCell x='488' y='182' />
<ChildCell x='83' y='469' />
<ChildCell x='95' y='393' />
<ChildCell x='95' y='328' />
<ChildCell x='95' y='263' />
<ChildCell x='95' y='198' />
<ChildCell x='95' y='78' />
<ChildCell x='95' y='136' />
<Settings maxCellsCount='7' needCellsCount='6' />
</map>